CHANGES.txt
MANIFEST.in
README.txt
bootstrap.py
buildout.cfg
setup.py
js/__init__.py
js.bootstrapdatepicker.egg-info/PKG-INFO
js.bootstrapdatepicker.egg-info/SOURCES.txt
js.bootstrapdatepicker.egg-info/dependency_links.txt
js.bootstrapdatepicker.egg-info/entry_points.txt
js.bootstrapdatepicker.egg-info/namespace_packages.txt
js.bootstrapdatepicker.egg-info/not-zip-safe
js.bootstrapdatepicker.egg-info/requires.txt
js.bootstrapdatepicker.egg-info/top_level.txt
js/bootstrapdatepicker/__init__.py
js/bootstrapdatepicker/test_bootstrapdatepicker.txt
js/bootstrapdatepicker/resources/bootstrap-datepicker.css
js/bootstrapdatepicker/resources/bootstrap-datepicker.js
js/bootstrapdatepicker/resources/bootstrap-datepicker.min.css
js/bootstrapdatepicker/resources/bootstrap-datepicker.min.js
js/bootstrapdatepicker/resources/locales/bootstrap-datepicker.bg.js
js/bootstrapdatepicker/resources/locales/bootstrap-datepicker.bg.min.js
js/bootstrapdatepicker/resources/locales/bootstrap-datepicker.ca.js
js/bootstrapdatepicker/resources/locales/bootstrap-datepicker.ca.min.js
js/bootstrapdatepicker/resources/locales/bootstrap-datepicker.cs.js
js/bootstrapdatepicker/resources/locales/bootstrap-datepicker.cs.min.js
js/bootstrapdatepicker/resources/locales/bootstrap-datepicker.da.js
js/bootstrapdatepicker/resources/locales/bootstrap-datepicker.da.min.js
js/bootstrapdatepicker/resources/locales/bootstrap-datepicker.de.js
js/bootstrapdatepicker/resources/locales/bootstrap-datepicker.de.min.js
js/bootstrapdatepicker/resources/locales/bootstrap-datepicker.el.js
js/bootstrapdatepicker/resources/locales/bootstrap-datepicker.el.min.js
js/bootstrapdatepicker/resources/locales/bootstrap-datepicker.es.js
js/bootstrapdatepicker/resources/locales/bootstrap-datepicker.es.min.js
js/bootstrapdatepicker/resources/locales/bootstrap-datepicker.et.js
js/bootstrapdatepicker/resources/locales/bootstrap-datepicker.et.min.js
js/bootstrapdatepicker/resources/locales/bootstrap-datepicker.fi.js
js/bootstrapdatepicker/resources/locales/bootstrap-datepicker.fi.min.js
js/bootstrapdatepicker/resources/locales/bootstrap-datepicker.fr.js
js/bootstrapdatepicker/resources/locales/bootstrap-datepicker.fr.min.js
js/bootstrapdatepicker/resources/locales/bootstrap-datepicker.he.js
js/bootstrapdatepicker/resources/locales/bootstrap-datepicker.he.min.js
