Metadata-Version: 1.1
Name: js.bootstrapdatepicker
Version: 1.1.3
Summary: Fanstatic packaging of bootstrap-datepicker.js.
Home-page: https://github.com/vangheem/js.bootstrapdatepicker
Author: Nathan Van Gheem
Author-email: vangheem@gmail.com
License: GPL
Download-URL: https://pypi.python.org/pypi/js.bootstrapdatepicker
Keywords: fanstatic bootstrap date widget
Platform: UNKNOWN
